divemarkdownit/__init__.py
divemarkdownit/_version.py
divemarkdownit/labextension/build_log.json
divemarkdownit/labextension/package.json
divemarkdownit/labextension/schemas/divemarkdownit/core.json
divemarkdownit/labextension/schemas/divemarkdownit/package.json.orig
divemarkdownit/labextension/static/lib_index_js.0820abc279e44c982591.js
divemarkdownit/labextension/static/lib_index_js.0820abc279e44c982591.js.map
divemarkdownit/labextension/static/node_modules_markdown-it-task-checkbox_index_js.ebd64da0584eefb7fc4e.js
divemarkdownit/labextension/static/node_modules_markdown-it-task-checkbox_index_js.ebd64da0584eefb7fc4e.js.map
divemarkdownit/labextension/static/remoteEntry.dd1fb26c3665399a7b1b.js
divemarkdownit/labextension/static/remoteEntry.dd1fb26c3665399a7b1b.js.map
divemarkdownit/labextension/static/style.js
divemarkdownit/labextension/static/style_index_js.55ca49e8d0eaf6ad2055.js
divemarkdownit/labextension/static/style_index_js.55ca49e8d0eaf6ad2055.js.map
divemarkdownit/labextension/static/vendors-node_modules_markdown-it-anchor_dist_markdownItAnchor_mjs.e0c489813daca131f3bb.js
divemarkdownit/labextension/static/vendors-node_modules_markdown-it-anchor_dist_markdownItAnchor_mjs.e0c489813daca131f3bb.js.map
divemarkdownit/labextension/static/vendors-node_modules_markdown-it-diagrams_lib_index_js.e0ccee7f48fd7a167c26.js
divemarkdownit/labextension/static/vendors-node_modules_markdown-it-diagrams_lib_index_js.e0ccee7f48fd7a167c26.js.map
divemarkdownit/labextension/static/vendors-node_modules_markdown-it-docutils_dist_css_style_min_css.882e9ac087517c92dedc.js
divemarkdownit/labextension/static/vendors-node_modules_markdown-it-docutils_dist_css_style_min_css.882e9ac087517c92dedc.js.map
divemarkdownit/labextension/static/vendors-node_modules_markdown-it-docutils_dist_esm_index_js.27a72a0250a4ba21d0f8.js
divemarkdownit/labextension/static/vendors-node_modules_markdown-it-docutils_dist_esm_index_js.27a72a0250a4ba21d0f8.js.map
divemarkdownit-0.0.1.dist-info/LICENSE
divemarkdownit-0.0.1.dist-info/METADATA
divemarkdownit-0.0.1.dist-info/WHEEL
divemarkdownit-0.0.1.dist-info/top_level.txt
divemarkdownit-0.0.1.dist-info/RECORD
